oss1/__init__.py
oss1/abc.py
oss1/local.py
oss1/s3.py
oss1-0.1.0.dist-info/METADATA
oss1-0.1.0.dist-info/WHEEL
oss1-0.1.0.dist-info/entry_points.txt
oss1-0.1.0.dist-info/RECORD
