Metadata-Version: 2.4
Name: oss1
Version: 0.1.0
Summary: Add your description here
Author-email: "董 福州 (DONG FUZHOU)" <sneakydog@yeah.net>
Requires-Python: >=3.10
Requires-Dist: aioboto3>=15.5.0
Requires-Dist: aiofiles>=25.1.0
Requires-Dist: minio>=7.2.20
Requires-Dist: mypy-boto3-s3>=1.42.10
